{
  "name": "bash-system-vibecoding-vault",
  "version": "1.0.0",
  "description": "🔥 Bash System - Vibecoding Vault Desktop App with Cal Character Layer",
  "main": "electron-main.js",
  "homepage": ".",
  "scripts": {
    "electron": "electron .",
    "electron-dev": "NODE_ENV=development electron .",
    "pack": "electron-builder --dir",
    "dist": "electron-builder",
    "dist-mac": "electron-builder --mac",
    "dist-win": "electron-builder --win",
    "dist-linux": "electron-builder --linux"
  },
  "build": {
    "appId": "com.vibecoding.bash-system",
    "productName": "Bash System - Vibecoding Vault",
    "directories": {
      "output": "dist"
    },
    "files": [
      "**/*",
      "!dist/**/*",
      "!node_modules/**/*"
    ],
    "mac": {
      "category": "public.app-category.developer-tools",
      "icon": "assets/icon.icns",
      "target": [
        {
          "target": "dmg",
          "arch": ["x64", "arm64"]
        }
      ]
    },
    "win": {
      "icon": "assets/icon.ico",
      "target": [
        {
          "target": "nsis",
          "arch": ["x64"]
        }
      ]
    },
    "linux": {
      "icon": "assets/icon.png",
      "target": [
        {
          "target": "AppImage",
          "arch": ["x64"]
        }
      ]
    }
  },
  "dependencies": {
    "express": "^4.18.2",
    "ws": "^8.14.2",
    "electron": "^27.0.0"
  },
  "devDependencies": {
    "electron-builder": "^24.6.4"
  }
}